debutils/__about__.py
debutils/__init__.py
debutils/exec.py
debutils/salsa.py
debutils/wnpp.py
debutils/cli/__init__.py
debutils/cli/itpwriter.py
debutils/cli/search_db.py
debutils/cli/wnpp_check.py
debutils/cli/go/__init__.py
debutils/cli/go/debian_name.py
debutils/cli/go/estimate.py
debutils/cli/go/make.py
debutils/go/__init__.py
debutils/go/debian.py
debutils/go/hosts.py
debutils/go/packages.py
debutils/go/session.py
debutils/go/vcs.py
debutils/licenses/AGPL-3+.txt
debutils/licenses/Apache-2.0.txt
debutils/licenses/BSD-2-Clause.txt
debutils/licenses/BSD-3-Clause.txt
debutils/licenses/Expat.txt
debutils/licenses/GPL-2+.txt
debutils/licenses/GPL-3+.txt
debutils/licenses/__init__.py
debutils/repos/__init__.py
debutils/repos/desc.py
debutils/templates/itp.jinja
debutils/templates/go/changelog.jinja
debutils/templates/go/copyright.jinja
debutils/templates/go/control/go_binary.jinja
debutils/templates/go/control/go_library.jinja
debutils/templates/go/control/header.jinja
debutils/templates/go/watch/git_commits.jinja
debutils/templates/go/watch/git_tags.jinja
debutils/templates/go/watch/github.jinja
debutils-0.2.2.dist-info/METADATA
debutils-0.2.2.dist-info/WHEEL
debutils-0.2.2.dist-info/entry_points.txt
debutils-0.2.2.dist-info/licenses/LICENSE
debutils-0.2.2.dist-info/licenses/LICENSE.md
debutils-0.2.2.dist-info/RECORD
