Metadata-Version: 2.1
Name: debutils
Version: 0.2.2
Summary: Utilities to help Debian package maintainers.
Project-URL: Documentation, https://codeberg.org/Maytha8/debutils#readme
Project-URL: Issues, https://codeberg.org/Maytha8/debutils/issues
Project-URL: Source, https://codeberg.org/Maytha8/debutils
Author-email: Maytham Alsudany <maytha8thedev@gmail.com>
License-Expression: GPL-3.0-or-later
License-File: LICENSE
License-File: LICENSE.md
Keywords: debian
Classifier: Development Status :: 4 - Beta
Classifier: Programming Language :: Python
Classifier: Programming Language :: Python :: 3.8
Classifier: Programming Language :: Python :: 3.9
Classifier: Programming Language :: Python :: 3.10
Classifier: Programming Language :: Python :: 3.11
Classifier: Programming Language :: Python :: 3.12
Classifier: Programming Language :: Python :: Implementation :: CPython
Classifier: Programming Language :: Python :: Implementation :: PyPy
Requires-Python: >=3.8
Requires-Dist: click
Requires-Dist: infer-license
Requires-Dist: jinja2
Requires-Dist: ldap3
Requires-Dist: packaging
Requires-Dist: python-debian
Requires-Dist: python-debianbts
Requires-Dist: questionary
Requires-Dist: requests
Requires-Dist: treelib
